Metadata-Version: 2.1
Name: pyfilters_lib
Version: 1.0.3
Summary: Python wrapper for Filters library
Home-page: https://gitlab.com/neurosdk2/neurosamples/-/tree/main/python
Author: Brainbit Inc.
Author-email: support@brainbit.com
License: MIT
Classifier: Programming Language :: Python :: 3
Classifier: License :: OSI Approved :: MIT License
Classifier: Operating System :: Microsoft :: Windows
Classifier: Operating System :: MacOS
Classifier: Intended Audience :: Developers
Requires-Python: >=3.7
